ModImpNet/__init__.py
ModImpNet/__main__.py
ModImpNet/_version.py
ModImpNet/modis_cli.py
ModImpNet/modis_download_all.py
ModImpNet/modis_download_conversion.py
ModImpNet/modis_full_nc_creation.py
ModImpNet/modis_nc_creation.py
ModImpNet/modis_requests.py
modimpnet-1.0.0.dist-info/licenses/LICENSE
modimpnet-1.0.0.dist-info/METADATA
modimpnet-1.0.0.dist-info/WHEEL
modimpnet-1.0.0.dist-info/entry_points.txt
modimpnet-1.0.0.dist-info/top_level.txt
modimpnet-1.0.0.dist-info/RECORD
