Metadata-Version: 2.4
Name: ModImpNet
Version: 1.0.0
Summary: ModImpNet (MODIS Import to netCDF): Import Snow cover NDSI and Land Surface Temperature (LST) from MODIS and produces a netCDF file from configuration files
Author-email: Victor Pozsgay <victor.pozsgay@carleton.ca>
License: GNU GENERAL PUBLIC LICENSE
Project-URL: Homepage, https://github.com/VictorPozsgay/ModImpNet
Classifier: Programming Language :: Python :: 3
Classifier: License :: OSI Approved :: GNU General Public License v3 (GPLv3)
Classifier: Operating System :: POSIX :: Linux
Classifier: Topic :: Scientific/Engineering :: GIS
Classifier: Topic :: Scientific/Engineering :: Atmospheric Science
Requires-Python: >=3.7
License-File: LICENSE
Requires-Dist: netCDF4
Requires-Dist: numpy
Requires-Dist: pandas
Requires-Dist: requests
Requires-Dist: toml
Requires-Dist: tomlkit
Dynamic: license-file
